google_datacatalog_connectors_commons-0.6.9-py3.6-nspkg.pth
google/datacatalog_connectors/commons/__init__.py
google/datacatalog_connectors/commons/datacatalog_facade.py
google/datacatalog_connectors/commons/cleanup/__init__.py
google/datacatalog_connectors/commons/cleanup/datacatalog_metadata_cleaner.py
google/datacatalog_connectors/commons/config/__init__.py
google/datacatalog_connectors/commons/config/yaml_config.py
google/datacatalog_connectors/commons/ingest/__init__.py
google/datacatalog_connectors/commons/ingest/datacatalog_metadata_ingestor.py
google/datacatalog_connectors/commons/monitoring/__init__.py
google/datacatalog_connectors/commons/monitoring/metrics_processor.py
google/datacatalog_connectors/commons/monitoring/monitoring_facade.py
google/datacatalog_connectors/commons/prepare/__init__.py
google/datacatalog_connectors/commons/prepare/assembled_entry_data.py
google/datacatalog_connectors/commons/prepare/base_entry_factory.py
google/datacatalog_connectors/commons/prepare/base_entry_relationship_mapper.py
google/datacatalog_connectors/commons/prepare/base_tag_factory.py
google/datacatalog_connectors/commons/prepare/base_tag_template_factory.py
google/datacatalog_connectors/commons/prepare/datacatalog_strings_helper.py
google/datacatalog_connectors/commons/utils/__init__.py
google/datacatalog_connectors/commons/utils/region_tag_helper.py
google/datacatalog_connectors/commons/utils/values_comparable_object.py
google_datacatalog_connectors_commons-0.6.9.dist-info/METADATA
google_datacatalog_connectors_commons-0.6.9.dist-info/WHEEL
google_datacatalog_connectors_commons-0.6.9.dist-info/namespace_packages.txt
google_datacatalog_connectors_commons-0.6.9.dist-info/top_level.txt
google_datacatalog_connectors_commons-0.6.9.dist-info/RECORD
