Metadata-Version: 2.1
Name: google-datacatalog-connectors-commons
Version: 0.6.9
Summary: Common resources for Data Catalog connectors
Home-page: UNKNOWN
Author: Google LLC
License: UNKNOWN
Platform: Posix; MacOS X; Windows
Classifier: Development Status :: 4 - Beta
Classifier: Intended Audience :: Developers
Classifier: License :: OSI Approved :: Apache Software License
Classifier: Programming Language :: Python
Classifier: Programming Language :: Python :: 2
Classifier: Programming Language :: Python :: 2.7
Classifier: Programming Language :: Python :: 3
Classifier: Programming Language :: Python :: 3.5
Classifier: Programming Language :: Python :: 3.6
Classifier: Programming Language :: Python :: 3.7
Classifier: Operating System :: OS Independent
Classifier: Topic :: Internet
Requires-Dist: google-cloud-monitoring (<2,>=1)
Requires-Dist: python-dateutil
Requires-Dist: google-cloud-datacatalog (<3,>=2)
Requires-Dist: pyYAML
